changeLogGenerator.py
changelog_generator_ciena-0.0.1a1.dist-info/METADATA
changelog_generator_ciena-0.0.1a1.dist-info/WHEEL
changelog_generator_ciena-0.0.1a1.dist-info/top_level.txt
changelog_generator_ciena-0.0.1a1.dist-info/RECORD
