Metadata-Version: 2.1
Name: changelog-generator-ciena
Version: 0.0.1a1
Summary: Changelog generator tool
Home-page: https://git.eng.blueplanet.com/ci-cd/changelog-generator
Author: Akshay
Author-email: aksrivas@ciena.com
License: Ciena
Platform: UNKNOWN
